mul_inout_regs/rtl/register16bit.sv
module register16bit 
(
	clk, rstn, in, out
);

input     clk;
input     rstn;
input  [15:0] in;
logic  [15:0] reg_value;
output [15:0] out;

always @(posedge clk or negedge rstn ) begin
	if (~rstn) begin
		reg_value   <= {16{1'b0}};
	end
	else begin
		reg_value   <= in;
	end
end

assign out = reg_value;

endmodule

mul_inout_regs/rtl/register8bit.sv
module register8bit 
(
	clk, rstn, in, out
);

input     clk;
input     rstn;
input  [7:0] in;
logic  [7:0] reg_value;
output [7:0] out;

always @(posedge clk or negedge rstn ) begin
	if (~rstn) begin
		reg_value   <= {8{1'b0}};
	end
	else begin
		reg_value   <= in;
	end
end

assign out = reg_value;

endmodule

mul_inout_regs/rtl/unsigned_mult.sv
module unsigned_mult 
(
	clk, rstn, a, b, out
);

input     clk;
input     rstn;
input  [7:0] a;
input  [7:0] b;
output [15:0] out;

logic  [7:0] a_reg;
logic  [7:0] b_reg;
logic  [15:0] mul_val;
logic  [15:0] out_reg;

// INPUT REGS 
register8bit regA (.clk(clk), .rstn(rstn), .in(a), .out(a_reg));

register8bit regB (.clk(clk), .rstn(rstn), .in(b), .out(b_reg));

// CORE
assign mul_val  = a_reg * b_reg;

// OUTPUT REG 
register16bit regOut (.clk(clk), .rstn(rstn), .in(mul_val), .out(out_reg));

assign out = out_reg;

  // Dump waves
  initial begin
    $dumpfile("dump.vcd");
    $dumpvars(1, unsigned_mult);
  end

endmodule

mul_inout_regs/tb/dump.vcd
$date
	Sat Jan  8 21:35:05 2022
$end
$version
	Icarus Verilog
$end
$timescale
	1ps
$end
$scope module unsigned_mult $end
$var wire 8 ! a [7:0] $end
$var wire 8 " b [7:0] $end
$var wire 1 # clk $end
$var wire 16 $ out [15:0] $end
$var wire 1 % rstn $end
$var wire 16 & out_reg [15:0] $end
$var wire 16 ' mul_val [15:0] $end
$var wire 8 ( b_reg [7:0] $end
$var wire 8 ) a_reg [7:0] $end
$upscope $end
$enddefinitions $end
#0
$dumpvars
bz )
bz (
bx '
bx &
z%
bx $
1#
bz "
bz !
$end
#1000
1%
#2000
b0 $
b0 &
b0 '
b0 (
b0 )
0%
#3000
1%
#5000
b11000111 !
b1001101 "
0#
#10000
b11101111011011 '
b11000111 )
b1001101 (
1#
#15000
0#
#20000
b11101111011011 $
b11101111011011 &
1#
#25000
b10100 !
b10110011 "
0#
#30000
b10100 )
b110111111100 '
b10110011 (
1#
#35000
0#
#40000
b110111111100 $
b110111111100 &
1#
#45000
b11101010 !
b10010010 "
0#
#50000
b11101010 )
b1000010101110100 '
b10010010 (
1#
#55000
0#
#60000
b1000010101110100 $
b1000010101110100 &
1#
#65000
b10000 !
b10000001 "
0#
#70000
b10000 )
b100000010000 '
b10000001 (
1#
#75000
0#
#80000
b100000010000 $
b100000010000 &
1#
#85000
b1010111 !
b10100011 "
0#
#90000
b1010111 )
b11011101100101 '
b10100011 (
1#
#95000
0#
#100000
b11011101100101 $
b11011101100101 &
1#
#105000
b11000111 !
b100101 "
0#
#110000
b11000111 )
b1110011000011 '
b100101 (
1#
#115000
0#
#120000
b1110011000011 $
b1110011000011 &
1#
#125000
b1111100 !
b11011010 "
0#
#130000
b1111100 )
b110100110011000 '
b11011010 (
1#
#135000
0#
#140000
b110100110011000 $
b110100110011000 &
1#
#145000
b111100 !
b10110000 "
0#
#150000
b111100 )
b10100101000000 '
b10110000 (
1#
#155000
0#
#160000
b10100101000000 $
b10100101000000 &
1#
#165000
b11000111 !
b10001111 "
0#
#170000
b11000111 )
b110111100101001 '
b10001111 (
1#
#175000
0#
#180000
b110111100101001 $
b110111100101001 &
1#
#185000
b11101 !
b11110011 "
0#
#190000
b11101 )
b1101110000111 '
b11110011 (
1#
#195000
0#
#200000
b1101110000111 $
b1101110000111 &
1#
#205000
b10100000 !
b10011110 "
0#
#210000
b10100000 )
b110001011000000 '
b10011110 (
1#
#215000
0#
#220000
b110001011000000 $
b110001011000000 &
1#
#225000
b11001100 !
b0 "
0#
#230000
b11001100 )
b0 '
b0 (
1#
#235000
0#
#240000
b0 $
b0 &
1#
#245000
b11000111 !
b111000 "
0#
#250000
b11000111 )
b10101110001000 '
b111000 (
1#
#255000
0#
#260000
b10101110001000 $
b10101110001000 &
1#
#265000
b1101000 !
b10000011 "
0#
#270000
b1101000 )
b11010100111000 '
b10000011 (
1#
#275000
0#
#280000
b11010100111000 $
b11010100111000 &
1#
#285000
b1011101 !
b11001100 "
0#
#290000
b1011101 )
b100101000011100 '
b11001100 (
1#
#295000
0#
#300000
b100101000011100 $
b100101000011100 &
1#
#305000
b11001111 !
b1000 "
0#
#310000
b11001111 )
b11001111000 '
b1000 (
1#
#315000
0#
#320000
b11001111000 $
b11001111000 &
1#
#325000
b101100 !
b10100 "
0#
#330000
b101100 )
b1101110000 '
b10100 (
1#
#335000
0#
#340000
b1101110000 $
b1101110000 &
1#
#345000
b10110100 !
b11111011 "
0#
#350000
b10110100 )
b1011000001111100 '
b11111011 (
1#
#355000
0#
#360000
b1011000001111100 $
b1011000001111100 &
1#
#365000
b1111000 !
b11101011 "
0#
#370000
b1111000 )
b110111000101000 '
b11101011 (
1#
#375000
0#
#380000
b110111000101000 $
b110111000101000 &
1#
#385000
b1001001 !
b10010000 "
0#
#390000
b1001001 )
b10100100010000 '
b10010000 (
1#
#395000
0#
#400000
b10100100010000 $
b10100100010000 &
1#
#405000
b10011000 !
b11001100 "
0#
#410000
b10011000 )
b111100100100000 '
b11001100 (
1#
#415000
0#
#420000
b111100100100000 $
b111100100100000 &
1#
#425000
b11110011 !
b11110 "
0#
#430000
b11110011 )
b1110001111010 '
b11110 (
1#
#435000
0#
#440000
b1110001111010 $
b1110001111010 &
1#
#445000
b1011011 !
b101111 "
0#
#450000
b1011011 )
b1000010110101 '
b101111 (
1#
#455000
0#
#460000
b1000010110101 $
b1000010110101 &
1#
#465000
b10001 !
b1010110 "
0#
#470000
b10001 )
b10110110110 '
b1010110 (
1#
#475000
0#
#480000
b10110110110 $
b10110110110 &
1#
#485000
b110000 !
b101100 "
0#
#490000
b110000 )
b100001000000 '
b101100 (
1#
#495000
0#
#500000
b100001000000 $
b100001000000 &
1#
#505000
b10111110 !
b1001010 "
0#
#510000
b10111110 )
b11011011101100 '
b1001010 (
1#
#515000
0#
#520000
b11011011101100 $
b11011011101100 &
1#
#525000
b11110110 !
b11100101 "
0#
#530000
b11110110 )
b1101110000001110 '
b11100101 (
1#
#535000
0#
#540000
b1101110000001110 $
b1101110000001110 &
1#
#545000
b10000 !
b10011101 "
0#
#550000
b10000 )
b100111010000 '
b10011101 (
1#
#555000
0#
#560000
b100111010000 $
b100111010000 &
1#
#565000
b11110110 !
b11110001 "
0#
#570000
b11110110 )
b1110011110010110 '
b11110001 (
1#
#575000
0#
#580000
b1110011110010110 $
b1110011110010110 &
1#
#585000
b11001110 !
b10100101 "
0#
#590000
b11001110 )
b1000010011000110 '
b10100101 (
1#
#595000
0#
#600000
b1000010011000110 $
b1000010011000110 &
1#
#605000
b10001101 !
b101010 "
0#
#610000
b10001101 )
b1011100100010 '
b101010 (
1#
#615000
0#
#620000
b1011100100010 $
b1011100100010 &
1#
#625000
b10000111 !
b11000000 "
0#
#630000
b10000111 )
b110010101000000 '
b11000000 (
1#
#635000
0#
#640000
b110010101000000 $
b110010101000000 &
1#
#645000
b111011 !
b11110110 "
0#
#650000
b111011 )
b11100010110010 '
b11110110 (
1#
#655000
0#
#660000
b11100010110010 $
b11100010110010 &
1#
#665000
b1101001 !
b10001101 "
0#
#670000
b1101001 )
b11100111010101 '
b10001101 (
1#
#675000
0#
#680000
b11100111010101 $
b11100111010101 &
1#
#685000
b11100010 !
b11110111 "
0#
#690000
b11100010 )
b1101101000001110 '
b11110111 (
1#
#695000
0#
#700000
b1101101000001110 $
b1101101000001110 &
1#
#705000
b10101001 !
b1100010 "
0#
#710000
b10101001 )
b100000010110010 '
b1100010 (
1#
#715000
0#
#720000
b100000010110010 $
b100000010110010 &
1#
#725000
b1100010 !
b11000110 "
0#
#730000
b1100010 )
b100101111001100 '
b11000110 (
1#
#735000
0#
#740000
b100101111001100 $
b100101111001100 &
1#
#745000
b1010100 !
b1101101 "
0#
#750000
b1010100 )
b10001111000100 '
b1101101 (
1#
#755000
0#
#760000
b10001111000100 $
b10001111000100 &
1#
#765000
b11100000 !
b1111110 "
0#
#770000
b11100000 )
b110111001000000 '
b1111110 (
1#
#775000
0#
#780000
b110111001000000 $
b110111001000000 &
1#
#785000
b10001010 !
b111000 "
0#
#790000
b10001010 )
b1111000110000 '
b111000 (
1#
#795000
0#
#800000
b1111000110000 $
b1111000110000 &
1#
#805000
b11011011 !
b11010101 "
0#
#810000
b11011011 )
b1011011000110111 '
b11010101 (
1#
#815000
0#
#820000
b1011011000110111 $
b1011011000110111 &
1#
#825000
b110000 !
b10111001 "
0#
#830000
b110000 )
b10001010110000 '
b10111001 (
1#
#835000
0#
#840000
b10001010110000 $
b10001010110000 &
1#
#845000
b1010101 !
b11010101 "
0#
#850000
b1010101 )
b100011010111001 '
b11010101 (
1#
#855000
0#
#860000
b100011010111001 $
b100011010111001 &
1#
#865000
b11100 !
b1110110 "
0#
#870000
b11100 )
b110011101000 '
b1110110 (
1#
#875000
0#
#880000
b110011101000 $
b110011101000 &
1#
#885000
b11111100 !
b10010000 "
0#
#890000
b11111100 )
b1000110111000000 '
b10010000 (
1#
#895000
0#
#900000
b1000110111000000 $
b1000110111000000 &
1#
#905000
b10011001 !
b110 "
0#
#910000
b10011001 )
b1110010110 '
b110 (
1#
#915000
0#
#920000
b1110010110 $
b1110010110 &
1#
#925000
b1101 !
b1101000 "
0#
#930000
b1101 )
b10101001000 '
b1101000 (
1#
#935000
0#
#940000
b10101001000 $
b10101001000 &
1#
#945000
b110111 !
b101010 "
0#
#950000
b110111 )
b100100000110 '
b101010 (
1#
#955000
0#
#960000
b100100000110 $
b100100000110 &
1#
#965000
b1001110 !
b1011111 "
0#
#970000
b1001110 )
b1110011110010 '
b1011111 (
1#
#975000
0#
#980000
b1110011110010 $
b1110011110010 &
1#
#985000
b11011111 !
b11011100 "
0#
#990000
b11011111 )
b1011111110100100 '
b11011100 (
1#
#995000
0#
#1000000
b1011111110100100 $
b1011111110100100 &
1#
#1005000
b1010001 !
b111101 "
0#
#1010000
b1010001 )
b1001101001101 '
b111101 (
1#
#1015000
0#
#1020000
b1001101001101 $
b1001101001101 &
1#
#1025000
b1111100 !
b1100100 "
0#
#1030000
b1111100 )
b11000001110000 '
b1100100 (
1#
#1035000
0#
#1040000
b11000001110000 $
b11000001110000 &
1#
#1045000
b11011110 !
b10100000 "
0#
#1050000
b11011110 )
b1000101011000000 '
b10100000 (
1#
#1055000
0#
#1060000
b1000101011000000 $
b1000101011000000 &
1#
#1065000
b11111000 !
b11010101 "
0#
#1070000
b11111000 )
b1100111001011000 '
b11010101 (
1#
#1075000
0#
#1080000
b1100111001011000 $
b1100111001011000 &
1#
#1085000
b11000100 !
b10111000 "
0#
#1090000
b11000100 )
b1000110011100000 '
b10111000 (
1#
#1095000
0#
#1100000
b1000110011100000 $
b1000110011100000 &
1#
#1105000
b11010010 !
b1000 "
0#
#1110000
b11010010 )
b11010010000 '
b1000 (
1#
#1115000
0#
#1120000
b11010010000 $
b11010010000 &
1#
#1125000
b1000011 !
b100001 "
0#
#1130000
b1000011 )
b100010100011 '
b100001 (
1#
#1135000
0#
#1140000
b100010100011 $
b100010100011 &
1#
#1145000
b1001001 !
b10001110 "
0#
#1150000
b1001001 )
b10100001111110 '
b10001110 (
1#
#1155000
0#
#1160000
b10100001111110 $
b10100001111110 &
1#
#1165000
b101110 !
b11010111 "
0#
#1170000
b101110 )
b10011010100010 '
b11010111 (
1#
#1175000
0#
#1180000
b10011010100010 $
b10011010100010 &
1#
#1185000
b11101010 !
b11010 "
0#
#1190000
b11101010 )
b1011111000100 '
b11010 (
1#
#1195000
0#
#1200000
b1011111000100 $
b1011111000100 &
1#
#1205000
b1101101 !
b1100 "
0#
#1210000
b1101101 )
b10100011100 '
b1100 (
1#
#1215000
0#
#1220000
b10100011100 $
b10100011100 &
1#
#1225000
b11001010 !
b10111111 "
0#
#1230000
b11001010 )
b1001011010110110 '
b10111111 (
1#
#1235000
0#
#1240000
b1001011010110110 $
b1001011010110110 &
1#
#1245000
b1001110 !
b10110100 "
0#
#1250000
b1001110 )
b11011011011000 '
b10110100 (
1#
#1255000
0#
#1260000
b11011011011000 $
b11011011011000 &
1#
#1265000
b100101 !
b1001110 "
0#
#1270000
b100101 )
b101101000110 '
b1001110 (
1#
#1275000
0#
#1280000
b101101000110 $
b101101000110 &
1#
#1285000
b11000111 !
b1000101 "
0#
#1290000
b11000111 )
b11010110100011 '
b1000101 (
1#
#1295000
0#
#1300000
b11010110100011 $
b11010110100011 &
1#
#1305000
b1011110 !
b10010001 "
0#
#1310000
b1011110 )
b11010100111110 '
b10010001 (
1#
#1315000
0#
#1320000
b11010100111110 $
b11010100111110 &
1#
#1325000
b1000000 !
b1111101 "
0#
#1330000
b1000000 )
b1111101000000 '
b1111101 (
1#
#1335000
0#
#1340000
b1111101000000 $
b1111101000000 &
1#
#1345000
b10011100 !
b10100001 "
0#
#1350000
b10011100 )
b110001000011100 '
b10100001 (
1#
#1355000
0#
#1360000
b110001000011100 $
b110001000011100 &
1#
#1365000
b101011 !
b1010110 "
0#
#1370000
b101011 )
b111001110010 '
b1010110 (
1#
#1375000
0#
#1380000
b111001110010 $
b111001110010 &
1#
#1385000
b1001011 !
b1001110 "
0#
#1390000
b1001011 )
b1011011011010 '
b1001110 (
1#
#1395000
0#
#1400000
b1011011011010 $
b1011011011010 &
1#
#1405000
b10100110 !
b1010010 "
0#
#1410000
b10100110 )
b11010100101100 '
b1010010 (
1#
#1415000
0#
#1420000
b11010100101100 $
b11010100101100 &
1#
#1425000
b1100010 !
b1100110 "
0#
#1430000
b1100010 )
b10011100001100 '
b1100110 (
1#
#1435000
0#
#1440000
b10011100001100 $
b10011100001100 &
1#
#1445000
b10110 !
b11111001 "
0#
#1450000
b10110 )
b1010101100110 '
b11111001 (
1#
#1455000
0#
#1460000
b1010101100110 $
b1010101100110 &
1#
#1465000
b1000010 !
b11001 "
0#
#1470000
b1000010 )
b11001110010 '
b11001 (
1#
#1475000
0#
#1480000
b11001110010 $
b11001110010 &
1#
#1485000
b10010000 !
b1111011 "
0#
#1490000
b10010000 )
b100010100110000 '
b1111011 (
1#
#1495000
0#
#1500000
b100010100110000 $
b100010100110000 &
1#
#1505000
b1100 !
b1100101 "
0#
#1510000
b1100 )
b10010111100 '
b1100101 (
1#
#1515000
0#
#1520000
b10010111100 $
b10010111100 &
1#
#1525000
b10011000 !
b11101111 "
0#
#1530000
b10011000 )
b1000110111101000 '
b11101111 (
1#
#1535000
0#
#1540000
b1000110111101000 $
b1000110111101000 &
1#
#1545000
b11111000 !
b11001 "
0#
#1550000
b11111000 )
b1100000111000 '
b11001 (
1#
#1555000
0#
#1560000
b1100000111000 $
b1100000111000 &
1#
#1565000
b1000110 !
b1110110 "
0#
#1570000
b1000110 )
b10000001000100 '
b1110110 (
1#
#1575000
0#
#1580000
b10000001000100 $
b10000001000100 &
1#
#1585000
b11100111 !
b111110 "
0#
#1590000
b11100111 )
b11011111110010 '
b111110 (
1#
#1595000
0#
#1600000
b11011111110010 $
b11011111110010 &
1#
#1605000
b10110101 !
b10011000 "
0#
#1610000
b10110101 )
b110101101111000 '
b10011000 (
1#
#1615000
0#
#1620000
b110101101111000 $
b110101101111000 &
1#
#1625000
b10001110 !
b1010 "
0#
#1630000
b10001110 )
b10110001100 '
b1010 (
1#
#1635000
0#
#1640000
b10110001100 $
b10110001100 &
1#
#1645000
b11101 !
b11011110 "
0#
#1650000
b11101 )
b1100100100110 '
b11011110 (
1#
#1655000
0#
#1660000
b1100100100110 $
b1100100100110 &
1#
#1665000
b1001101 !
b110101 "
0#
#1670000
b1001101 )
b111111110001 '
b110101 (
1#
#1675000
0#
#1680000
b111111110001 $
b111111110001 &
1#
#1685000
b11011001 !
b100 "
0#
#1690000
b11011001 )
b1101100100 '
b100 (
1#
#1695000
0#
#1700000
b1101100100 $
b1101100100 &
1#
#1705000
b10100010 !
b1000000 "
0#
#1710000
b10100010 )
b10100010000000 '
b1000000 (
1#
#1715000
0#
#1720000
b10100010000000 $
b10100010000000 &
1#
#1725000
b10100101 !
b1101110 "
0#
#1730000
b10100101 )
b100011011100110 '
b1101110 (
1#
#1735000
0#
#1740000
b100011011100110 $
b100011011100110 &
1#
#1745000
b10001111 !
b1111010 "
0#
#1750000
b10001111 )
b100010000100110 '
b1111010 (
1#
#1755000
0#
#1760000
b100010000100110 $
b100010000100110 &
1#
#1765000
b100011 !
b11111 "
0#
#1770000
b100011 )
b10000111101 '
b11111 (
1#
#1775000
0#
#1780000
b10000111101 $
b10000111101 &
1#
#1785000
b100000 !
b1011011 "
0#
#1790000
b100000 )
b101101100000 '
b1011011 (
1#
#1795000
0#
#1800000
b101101100000 $
b101101100000 &
1#
#1805000
b1011011 !
b10110001 "
0#
#1810000
b1011011 )
b11111011101011 '
b10110001 (
1#
#1815000
0#
#1820000
b11111011101011 $
b11111011101011 &
1#
#1825000
b11111101 !
b10110110 "
0#
#1830000
b11111101 )
b1011001111011110 '
b10110110 (
1#
#1835000
0#
#1840000
b1011001111011110 $
b1011001111011110 &
1#
#1845000
b11110110 !
b11000001 "
0#
#1850000
b11110110 )
b1011100101110110 '
b11000001 (
1#
#1855000
0#
#1860000
b1011100101110110 $
b1011100101110110 &
1#
#1865000
b10011100 !
b10111110 "
0#
#1870000
b10011100 )
b111001111001000 '
b10111110 (
1#
#1875000
0#
#1880000
b111001111001000 $
b111001111001000 &
1#
#1885000
b10100011 !
b11111111 "
0#
#1890000
b10100011 )
b1010001001011101 '
b11111111 (
1#
#1895000
0#
#1900000
b1010001001011101 $
b1010001001011101 &
1#
#1905000
b1101011 !
b100100 "
0#
#1910000
b1101011 )
b111100001100 '
b100100 (
1#
#1915000
0#
#1920000
b111100001100 $
b111100001100 &
1#
#1925000
b11011010 !
b10111 "
0#
#1930000
b11011010 )
b1001110010110 '
b10111 (
1#
#1935000
0#
#1940000
b1001110010110 $
b1001110010110 &
1#
#1945000
b11111 !
b11010001 "
0#
#1950000
b11111 )
b1100101001111 '
b11010001 (
1#
#1955000
0#
#1960000
b1100101001111 $
b1100101001111 &
1#
#1965000
b10100110 !
b10111 "
0#
#1970000
b10100110 )
b111011101010 '
b10111 (
1#
#1975000
0#
#1980000
b111011101010 $
b111011101010 &
1#
#1985000
b1110001 !
b1010 "
0#
#1990000
b1110001 )
b10001101010 '
b1010 (
1#
#1995000
0#
#2000000
b10001101010 $
b10001101010 &
1#
#2005000
0#
#2005001
1#
#2007001
b0 $
b0 &
b0 (
b0 '
b0 )
0%
#2008001
1%
#2010001
b0 !
b0 "
0#
#2015001
1#
#2020001
0#
#2025001
1#
#2030001
0#
#2035001
1#
#2040001
b11111111 !
b11111111 "
0#
#2045001
b1111111000000001 '
b11111111 (
b11111111 )
1#
#2050001
0#
#2055001
b1111111000000001 $
b1111111000000001 &
1#
#2060001
0#
#2065001
1#
#2070001
0#
#2075001
1#
#2080001
b0 !
b0 "
0#
#2085001
b0 (
b0 '
b0 )
1#
#2090001
0#
#2095001
b0 $
b0 &
1#
#2100001
b11111111 !
0#
#2105001
b11111111 )
1#
#2110001
0#
#2115001
1#
#2120001
b0 !
b11111111 "
0#
#2125001
b11111111 (
b0 )
1#
#2130001
0#
#2135001
1#
#2140001
b11111111 !
b0 "
0#
#2145001
b0 (
b0 '
b11111111 )
1#
#2150001
0#
#2155001
1#
#2160001
b0 !
b11111111 "
0#
#2165001
b11111111 (
b0 )
1#
